fml_doc_gen/__init__.py
fml_doc_gen/autogen.py
fml_doc_gen/fml_doc_gen.py
fml_doc_gen/func_dto.py
fml_doc_gen/generate_template.py
fml_doc_gen/read_user_function.py
fml_doc_gen/write_docstring_to_file.py
fml_doc_gen-3.1.1.dist-info/LICENSE
fml_doc_gen-3.1.1.dist-info/METADATA
fml_doc_gen-3.1.1.dist-info/WHEEL
fml_doc_gen-3.1.1.dist-info/RECORD
