Metadata-Version: 2.3
Name: fml_doc_gen
Version: 3.1.1
Summary: doc string generator
License: MIT
Author: Farhan Faisal
Requires-Python: >=3.10,<4.0
Classifier: License :: OSI Approved :: MIT License
Classifier: Programming Language :: Python :: 3
Classifier: Programming Language :: Python :: 3.10
Classifier: Programming Language :: Python :: 3.11
Classifier: Programming Language :: Python :: 3.12
Classifier: Programming Language :: Python :: 3.13
Requires-Dist: autoapi (>=2.0.1,<3.0.0)
Requires-Dist: colorama (>=0.4.6,<0.5.0)
Requires-Dist: myst-nb (>=1.1.2,<2.0.0)
Requires-Dist: openai (>=1.60.2,<2.0.0)
Requires-Dist: poetry (>=2.0.0,<3.0.0)
Requires-Dist: python-dotenv (>=1.0.1,<2.0.0)
